<annotation>
	<folder></folder>
	<filename>Ac-N093_jpg.rf.3cc97455788a0c7e3ebd8d488904f46d.jpg</filename>
	<path>Ac-N093_jpg.rf.3cc97455788a0c7e3ebd8d488904f46d.jpg</path>
	<source>
		<database>roboflow.com</database>
	</source>
	<size>
		<width>640</width>
		<height>640</height>
		<depth>3</depth>
	</size>
	<segmented>0</segmented>
	<object>
		<name>Ac</name>
		<pose>Unspecified</pose>
		<truncated>0</truncated>
		<difficult>0</difficult>
		<occluded>0</occluded>
		<bndbox>
			<xmin>318</xmin>
			<xmax>608</xmax>
			<ymin>5</ymin>
			<ymax>168</ymax>
		</bndbox>
	</object>
</annotation>
