<annotation>
	<folder></folder>
	<filename>Ci-N044_jpg.rf.b82a8972cd84b7d49661000e8511ad3f.jpg</filename>
	<path>Ci-N044_jpg.rf.b82a8972cd84b7d49661000e8511ad3f.jpg</path>
	<source>
		<database>roboflow.com</database>
	</source>
	<size>
		<width>640</width>
		<height>640</height>
		<depth>3</depth>
	</size>
	<segmented>0</segmented>
	<object>
		<name>Ci</name>
		<pose>Unspecified</pose>
		<truncated>0</truncated>
		<difficult>0</difficult>
		<occluded>0</occluded>
		<bndbox>
			<xmin>1</xmin>
			<xmax>641</xmax>
			<ymin>55</ymin>
			<ymax>519</ymax>
		</bndbox>
	</object>
</annotation>
