<annotation>
	<folder></folder>
	<filename>Ns-N006_jpg.rf.886936a91b7db5e7e529a2bbe9b85b23.jpg</filename>
	<path>Ns-N006_jpg.rf.886936a91b7db5e7e529a2bbe9b85b23.jpg</path>
	<source>
		<database>roboflow.com</database>
	</source>
	<size>
		<width>640</width>
		<height>640</height>
		<depth>3</depth>
	</size>
	<segmented>0</segmented>
	<object>
		<name>Ns</name>
		<pose>Unspecified</pose>
		<truncated>0</truncated>
		<difficult>0</difficult>
		<occluded>0</occluded>
		<bndbox>
			<xmin>1</xmin>
			<xmax>641</xmax>
			<ymin>70</ymin>
			<ymax>584</ymax>
		</bndbox>
	</object>
</annotation>
